SAMstats/__init__.py
SAMstatsParallel/__init__.py
SAMstats-0.2.2.dist-info/METADATA
SAMstats-0.2.2.dist-info/WHEEL
SAMstats-0.2.2.dist-info/dependency_links.txt
SAMstats-0.2.2.dist-info/entry_points.txt
SAMstats-0.2.2.dist-info/top_level.txt
SAMstats-0.2.2.dist-info/RECORD
