Metadata-Version: 2.1
Name: SAMstats
Version: 0.2.2
Summary: SAM file alignment statistics at the read level
Home-page: UNKNOWN
Author: UNKNOWN
Author-email: UNKNOWN
License: UNKNOWN
Platform: UNKNOWN
Requires-Dist: multiprocess
